{
    "question": "Click the Exhibit button.<br>Given the HTML form:<br>1. <html>\n2. <body>\n3. <form action=\u201dsubmit.jsp\u201d>\n4. Name: <input type=\u201dtext\u201d name=\u201di1\u2033><br>\n5. Price: <input type=\u201dtext\u201d name=\u201di2\u2033><br>\n6. <input type=\u201dsubmit\u201d>\n7. </form>\n8. </body>\n9. </html>\nAssume the product attribute does NOT yet exist in any scope.\nWhich code snippet, in submit.jsp, instantiates an instance of com.example.Product that contains\nthe results of the form submission?\n<a href=\"//cdn.briefmenow.org/wp-content/uploads/1z0-858/19.jpg\"><img alt=\"\" class=\"aligncenter size-full\" src=\"//cdn.briefmenow.org/wp-content/uploads/1z0-858/19.jpg\"/></a>",
    "options": {
        "A": "<jsp:useBean id=\u201dcom.example.Product\u201d /> <jsp:setProperty name=\u201dproduct\u201d property=\u201d*\u201d />",
        "B": "<jsp:useBean id=\u201dproduct\u201d class=\u201dcom.example.Product\u201d /> ${product.name = param.i1} ${product.price = param.i2}",
        "C": "<jsp:useBean id=\u201dproduct\u201d class=\u201dcom.example.Product\u201d> <jsp:setProperty name=\u201dproduct\u201d property=\u201dname\u201d param=\u201di1\u2033 /> <jsp:setProperty name=\u201dproduct\u201d property=\u201dprice\u201d param=\u201di2\u2033 /> </jsp:useBean>",
        "D": "<jsp:useBean id=\u201dproduct\u201d type=\u201dcom.example.Product\u201d> <jsp:setProperty name=\u201dproduct\u201d property=\u201dname\u201d value=\u201d<%= request.getParameter( \u201ci1\u2033 ) %>\u201d /> <jsp:setProperty name=\u201dproduct\u201d property=\u201dprice\u201d value=\u201d<%= request.getParameter( \u201ci2\u2033 ) %>\u201d /> </jsp:useBean>"
    },
    "answer": "C",
    "multi": false
}