{
    "question": "You need to create a JavaBean object that is used only within the current JSP page. It must NOT<br>be accessible to any other page including those that this page might import. Which JSP standard<br>action can accomplish this goal?",
    "options": {
        "A": "<jsp:useBean id=\u2019pageBean\u2019 type=\u2019com.example.MyBean\u2019 />",
        "B": "<jsp:useBean id=\u2019pageBean\u2019 class=\u2019com.example.MyBean\u2019 />",
        "C": "<jsp:makeBean id=\u2019pageBean\u2019 type=\u2019com.example.MyBean\u2019 />",
        "D": "<jsp:makeBean id=\u2019pageBean\u2019 class=\u2019com.example.MyBean\u2019 />",
        "E": "<jsp:useBean name=\u2019pageBean\u2019 class=\u2019com.example.MyBean\u2019 />",
        "F": "<jsp:makeBean name=\u2019pageBean\u2019 class=\u2019com.example.MyBean\u2019 />"
    },
    "answer": "B",
    "multi": false
}